klass_registry/__init__.py
klass_registry/auto_register.py
klass_registry/cache.py
klass_registry/entry_points.py
klass_registry/patcher.py
klass_registry/registry.py
klass_registry-2.2.2.dist-info/LICENSE
klass_registry-2.2.2.dist-info/METADATA
klass_registry-2.2.2.dist-info/WHEEL
klass_registry-2.2.2.dist-info/top_level.txt
klass_registry-2.2.2.dist-info/RECORD
