Metadata-Version: 2.1
Name: klass-registry
Version: 2.2.2
Summary: Factory+Registry pattern for Python classes.
Home-page: https://klass-registry.readthedocs.io/
Author: Igor Quintanilha
Author-email: igormq@poli.ufrj.br
License: MIT
Keywords: registry pattern
Platform: UNKNOWN
Classifier: Development Status :: 5 - Production/Stable
Classifier: Intended Audience :: Developers
Classifier: License :: OSI Approved :: MIT License
Classifier: Programming Language :: Python :: 2
Classifier: Programming Language :: Python :: 2.7
Classifier: Programming Language :: Python :: 3
Classifier: Programming Language :: Python :: 3.5
Classifier: Programming Language :: Python :: 3.6
Classifier: Programming Language :: Python :: 3.7
Classifier: Topic :: Software Development :: Libraries :: Python Modules
Requires-Dist: six
Requires-Dist: typing ; python_version < "3.0"
Provides-Extra: docs-builder
Requires-Dist: sphinx ; extra == 'docs-builder'
Requires-Dist: sphinx-rtd-theme ; extra == 'docs-builder'
Provides-Extra: test-runner
Requires-Dist: detox ; extra == 'test-runner'
